SmartMixin/UA.py
SmartMixin/__init__.py
SmartMixin/handler.py
SmartMixin/helpers.py
SmartMixin/serialization.py
smartmixin-2.4.0.dist-info/licenses/LICENSE
smartmixin-2.4.0.dist-info/METADATA
smartmixin-2.4.0.dist-info/WHEEL
smartmixin-2.4.0.dist-info/top_level.txt
smartmixin-2.4.0.dist-info/RECORD
