Metadata-Version: 2.4
Name: SmartMixin
Version: 2.4.0
Summary: A Python library for Clash configuration file manipulation.
Home-page: https://github.com/UFervor/SmartMixin
Author: _Fervor_
Requires-Python: >=3.10.0
License-File: LICENSE
Requires-Dist: requests
Requires-Dist: pyyaml
Dynamic: author
Dynamic: description
Dynamic: description-content-type
Dynamic: home-page
Dynamic: license-file
Dynamic: requires-dist
Dynamic: requires-python
Dynamic: summary
